{"genres":["Hardstyle","Happy Hardcore","Frenchcore"],"name":"DJ Keppy","logo":"https:\/\/cdn.discordapp.com\/attachments\/1235015589878300765\/1235016158940237844\/DJ_Keppy_Logo_White.png?ex=6632d5ed&is=6631846d&hm=0f72c8e5a5f167502930a1a0e9137722be7a3bb87ecc080d68a1ecf212375155&","demoSets":["https:\/\/youtu.be\/F5wip2vZWFQ?si=tFkFYNQ-Oh-VVfpe"],"socials":["https:\/\/www.twitch.tv\/keppyroo","https:\/\/twitter.com\/KeppyRoo","https:\/\/bsky.app\/profile\/keppyroo.bsky.social"],"vrcName":"Whisp Reedwell"}